pyelucidate/__init__.py
pyelucidate/pyelucidate.py
pyelucidate-0.3.0.dist-info/AUTHORS.rst
pyelucidate-0.3.0.dist-info/LICENSE
pyelucidate-0.3.0.dist-info/LICENSE.rst
pyelucidate-0.3.0.dist-info/METADATA
pyelucidate-0.3.0.dist-info/WHEEL
pyelucidate-0.3.0.dist-info/top_level.txt
pyelucidate-0.3.0.dist-info/RECORD
