Metadata-Version: 2.1
Name: pyelucidate
Version: 0.3.0
Summary: Open Source Python Tools for the Elucidate Annotation Server.
Home-page: https://github.com/digirati-co-uk/pyelucidate
Author: Matt McGrattan
Author-email: matt.mcgrattan@digirati.com
License: MIT
Keywords: pyelucidate
Platform: UNKNOWN
Classifier: Development Status :: 2 - Pre-Alpha
Classifier: Intended Audience :: Developers
Classifier: License :: OSI Approved :: MIT License
Classifier: Natural Language :: English
Classifier: Programming Language :: Python :: 3
Classifier: Programming Language :: Python :: 3.5
Classifier: Programming Language :: Python :: 3.6
Classifier: Programming Language :: Python :: 3.7
Classifier: Programming Language :: Python :: Implementation :: PyPy
Requires-Dist: aiohttp (>=3.4.4)
Requires-Dist: requests (>=2.20.1)
